sprt/__init__.py
sprt/__main__.py
sprt/arguments.py
sprt/envs.py
sprt/exceptions.py
sprt/loader.py
sprt/log.py
sprt/master.py
sprt/server.py
sprt/storage.py
sprt/testing.py
sprt/utils.py
sprt/version.py
suanpan_sprt-0.7.3.dist-info/METADATA
suanpan_sprt-0.7.3.dist-info/WHEEL
suanpan_sprt-0.7.3.dist-info/entry_points.txt
suanpan_sprt-0.7.3.dist-info/top_level.txt
suanpan_sprt-0.7.3.dist-info/RECORD
