Metadata-Version: 2.1
Name: suanpan-sprt
Version: 0.7.3
Summary: A framework for invoking functions over HTTP
Home-page: https://gitlab-sp.xuelangyun.com/xuelang-group/suanpan-functional-python
Author: Guangyuan Lu
Author-email: mocheng.lgy@xuelangyun.com
Keywords: suanpan,faas,functions
Requires-Python: >=3.7
Requires-Dist: Quart[dotenv] (~=0.18.3)
Requires-Dist: quart-schema (~=0.14.3)
Requires-Dist: hypercorn (~=0.14.3)
Requires-Dist: click (~=8.1.3)
Requires-Dist: pydantic (~=1.10.5)
Requires-Dist: python-socketio[client] (~=5.8.0)
Requires-Dist: python-dotenv (~=0.21.1)
Requires-Dist: minio (~=7.1.14)
